ctyunsdk_image20220909/__init__.py
ctyunsdk_image20220909/apis/__init__.py
ctyunsdk_image20220909/apis/apis.py
ctyunsdk_image20220909/apis/ctimage_create_ecs_system_disk_image_api.py
ctyunsdk_image20220909/apis/ctimage_delete_image_api.py
ctyunsdk_image20220909/apis/ctimage_list_image_shares_api.py
ctyunsdk_image20220909/apis/ctimage_list_images_api.py
ctyunsdk_image20220909/apis/ctimage_share_image_api.py
ctyunsdk_image20220909/apis/ctimage_unshare_image_api.py
ctyunsdk_image20220909/core/__init__.py
ctyunsdk_image20220909/core/client.py
ctyunsdk_image20220909/core/credential.py
ctyunsdk_image20220909/core/ctapi_sdk_python.py
ctyunsdk_image20220909/core/exception.py
ctyunsdk_image20220909/core/http_methods.py
ctyunsdk_image20220909/core/request.py
ctyunsdk_image20220909/core/request_builder.py
ctyunsdk_image20220909/core/request_template.py
ctyunsdk_image20220909/core/signer.py
ctyunsdk_image20220909/core/utils.py
ctyunsdk_image20220909-1.0.0.dist-info/LICENSE.txt
ctyunsdk_image20220909-1.0.0.dist-info/METADATA
ctyunsdk_image20220909-1.0.0.dist-info/WHEEL
ctyunsdk_image20220909-1.0.0.dist-info/top_level.txt
ctyunsdk_image20220909-1.0.0.dist-info/RECORD
